bytedforge_tracing/__init__.py
bytedforge_tracing-0.0.1.dist-info/METADATA
bytedforge_tracing-0.0.1.dist-info/WHEEL
bytedforge_tracing-0.0.1.dist-info/top_level.txt
bytedforge_tracing-0.0.1.dist-info/RECORD
